{
  "best_global_step": 2858,
  "best_metric": 0.02609844133257866,
  "best_model_checkpoint": "./results/checkpoint-2858",
  "epoch": 1.0,
  "eval_steps": 500,
  "global_step": 2858,
  "is_hyper_param_search": false,
  "is_local_process_zero": true,
  "is_world_process_zero": true,
  "log_history": [
    {
      "epoch": 0.17494751574527642,
      "grad_norm": 6.097597599029541,
      "learning_rate": 1.8415107659724677e-05,
      "loss": 0.0445,
      "step": 500
    },
    {
      "epoch": 0.34989503149055284,
      "grad_norm": 2.5961101055145264,
      "learning_rate": 1.6650194140487118e-05,
      "loss": 0.0302,
      "step": 1000
    },
    {
      "epoch": 0.5248425472358292,
      "grad_norm": 2.165374755859375,
      "learning_rate": 1.488528062124956e-05,
      "loss": 0.024,
      "step": 1500
    },
    {
      "epoch": 0.6997900629811057,
      "grad_norm": 0.8424955606460571,
      "learning_rate": 1.3120367102012002e-05,
      "loss": 0.0246,
      "step": 2000
    },
    {
      "epoch": 0.8747375787263821,
      "grad_norm": 1.847594141960144,
      "learning_rate": 1.1355453582774444e-05,
      "loss": 0.0224,
      "step": 2500
    },
    {
      "epoch": 1.0,
      "eval_loss": 0.02609844133257866,
      "eval_runtime": 142.6293,
      "eval_samples_per_second": 8.911,
      "eval_steps_per_second": 2.23,
      "step": 2858
    }
  ],
  "logging_steps": 500,
  "max_steps": 5716,
  "num_input_tokens_seen": 0,
  "num_train_epochs": 2,
  "save_steps": 500,
  "stateful_callbacks": {
    "TrainerControl": {
      "args": {
        "should_epoch_stop": false,
        "should_evaluate": false,
        "should_log": false,
        "should_save": true,
        "should_training_stop": false
      },
      "attributes": {}
    }
  },
  "total_flos": 3007858578284544.0,
  "train_batch_size": 4,
  "trial_name": null,
  "trial_params": null
}
